[
  {
    "server_id": "ums_server_0",
    "endpoint": [
      {
        "protocol": "GW",
        "outer": "dev.tiejin.cn:18081",
        "ssl": "dev.tiejin.cn:14081",
        "inter": "10.0.1.7:8081"
      },
      {
        "protocol": "WEB_SOCKET",
        "outer": "dev.tiejin.cn:18088",
        "ssl": "dev.tiejin.cn:14088",
        "inter": "10.0.1.7:8088"
      },
      {
        "protocol": "RPC",
        "outer": "10.0.1.7:8082",
        "inter": "10.0.1.7:8082"
      }
    ]
  },
  {
    "server_id": "ums_server_1",
    "endpoint": [
      {
        "protocol": "GW",
        "outer": "dev.tiejin.cn:18081",
        "ssl": "dev.tiejin.cn:14081",
        "inter": "10.0.1.7:8181"
      },
      {
        "protocol": "WEB_SOCKET",
        "outer": "dev.tiejin.cn:18088",
        "ssl": "dev.tiejin.cn:14088",
        "inter": "10.0.1.7:8188"
      },
      {
        "protocol": "RPC",
        "outer": "10.0.1.7:8182",
        "inter": "10.0.1.7:8182"
      }
    ]
  }
]
